{
  "stats": {
    "suites": 3,
    "tests": 10,
    "passes": 10,
    "pending": 0,
    "failures": 0,
    "start": "2021-10-28T11:22:46.196Z",
    "end": "2021-10-28T11:31:15.974Z",
    "duration": 105956,
    "testsRegistered": 10,
    "passPercent": 100,
    "pendingPercent": 0,
    "other": 0,
    "hasOther": false,
    "skipped": 0,
    "hasSkipped": false
  },
  "results": [
    {
      "uuid": "1474dbc8-7bf1-4b8c-8f59-d2e9b9fbf420",
      "title": "",
      "fullFile": "cypress/integration/regressionpageobjects.spec.js",
      "file": "cypress/integration/regressionpageobjects.spec.js",
      "beforeHooks": [],
      "afterHooks": [],
      "tests": [],
      "suites": [
        {
          "uuid": "9f54cda8-db99-423f-a717-404c78d660d8",
          "title": " Test suite",
          "fullFile": "",
          "file": "",
          "beforeHooks": [],
          "afterHooks": [],
          "tests": [
            {
              "title": "login, visit pages and logut",
              "fullTitle": " Test suite login, visit pages and logut",
              "timedOut": null,
              "duration": 14111,
              "state": "passed",
              "speed": "slow",
              "pass": true,
              "fail": false,
              "pending": false,
              "context": null,
              "code": "indexfunctions.performValidLogin(cy, targets.username, targets.password, 'Tester Hotel Overview');\ndashBoardfunctions.rooms(cy, 'Rooms');\ndashBoardfunctions.clients(cy, 'Clients');\ndashBoardfunctions.bills(cy, 'Bills');\ndashBoardfunctions.reservations(cy, 'Reservations');\ndashBoardfunctions.logout(cy, 'Login');",
              "err": {},
              "uuid": "68b078e1-22c2-49e9-8140-84539969a198",
              "parentUUID": "9f54cda8-db99-423f-a717-404c78d660d8",
              "isHook": false,
              "skipped": false
            },
            {
              "title": "edit a room",
              "fullTitle": " Test suite edit a room",
              "timedOut": null,
              "duration": 8918,
              "state": "passed",
              "speed": "slow",
              "pass": true,
              "fail": false,
              "pending": false,
              "context": null,
              "code": "indexfunctions.performValidLogin(cy, targets.username, targets.password, 'Tester Hotel Overview');\nroomsPagefunctions.editrooms(cy, 'Rooms');\ndashBoardfunctions.logout(cy, 'Login');",
              "err": {},
              "uuid": "4f03b5fe-aa09-4cf6-bbfd-e1717b31074c",
              "parentUUID": "9f54cda8-db99-423f-a717-404c78d660d8",
              "isHook": false,
              "skipped": false
            },
            {
              "title": "create client",
              "fullTitle": " Test suite create client",
              "timedOut": null,
              "duration": 8164,
              "state": "passed",
              "speed": "slow",
              "pass": true,
              "fail": false,
              "pending": false,
              "context": null,
              "code": "indexfunctions.performValidLogin(cy, targets.username, targets.password, 'Tester Hotel Overview');\nclientsPagefunctions.createClient(cy, 'Clients');\ndashBoardfunctions.logout(cy, 'Login');",
              "err": {},
              "uuid": "6a6d2cfd-6ec4-4b81-b970-e66d2df97ace",
              "parentUUID": "9f54cda8-db99-423f-a717-404c78d660d8",
              "isHook": false,
              "skipped": false
            }
          ],
          "suites": [],
          "passes": [
            "68b078e1-22c2-49e9-8140-84539969a198",
            "4f03b5fe-aa09-4cf6-bbfd-e1717b31074c",
            "6a6d2cfd-6ec4-4b81-b970-e66d2df97ace"
          ],
          "failures": [],
          "pending": [],
          "skipped": [],
          "duration": 31193,
          "root": false,
          "rootEmpty": false,
          "_timeout": 2000
        }
      ],
      "passes": [],
      "failures": [],
      "pending": [],
      "skipped": [],
      "duration": 0,
      "root": true,
      "rootEmpty": true,
      "_timeout": 2000
    },
    {
      "uuid": "55083a2e-4afe-43d6-b907-aa00616f7383",
      "title": "",
      "fullFile": "cypress/integration/regressionpageobjects2.spec.js",
      "file": "cypress/integration/regressionpageobjects2.spec.js",
      "beforeHooks": [],
      "afterHooks": [],
      "tests": [],
      "suites": [
        {
          "uuid": "52e1a080-3fb3-42db-bb3d-a1da20bbcfaf",
          "title": " Test suite 2",
          "fullFile": "",
          "file": "",
          "beforeHooks": [],
          "afterHooks": [],
          "tests": [
            {
              "title": "edit client",
              "fullTitle": " Test suite 2 edit client",
              "timedOut": null,
              "duration": 11922,
              "state": "passed",
              "speed": "slow",
              "pass": true,
              "fail": false,
              "pending": false,
              "context": null,
              "code": "indexfunctions.performValidLogin(cy, targets.username, targets.password, 'Tester Hotel Overview');\nclientsPagefunctions.editClient(cy, 'Clients');\ndashBoardfunctions.logout(cy, 'Login');",
              "err": {},
              "uuid": "c81282ec-6921-43c7-958d-5b294262e637",
              "parentUUID": "52e1a080-3fb3-42db-bb3d-a1da20bbcfaf",
              "isHook": false,
              "skipped": false
            },
            {
              "title": "create room",
              "fullTitle": " Test suite 2 create room",
              "timedOut": null,
              "duration": 12102,
              "state": "passed",
              "speed": "slow",
              "pass": true,
              "fail": false,
              "pending": false,
              "context": null,
              "code": "indexfunctions.performValidLogin(cy, targets.username, targets.password, 'Tester Hotel Overview');\nroomsPagefunctions.createaroom(cy, 'Rooms');\ndashBoardfunctions.logout(cy, 'Login');",
              "err": {},
              "uuid": "70560249-4ff8-41dd-8758-9bb41c972da1",
              "parentUUID": "52e1a080-3fb3-42db-bb3d-a1da20bbcfaf",
              "isHook": false,
              "skipped": false
            },
            {
              "title": "create bill",
              "fullTitle": " Test suite 2 create bill",
              "timedOut": null,
              "duration": 6916,
              "state": "passed",
              "speed": "slow",
              "pass": true,
              "fail": false,
              "pending": false,
              "context": null,
              "code": "indexfunctions.performValidLogin(cy, targets.username, targets.password, 'Tester Hotel Overview');\nbillsPagefunctions.createBill(cy, 'Bills');\ndashBoardfunctions.logout(cy, 'Login');",
              "err": {},
              "uuid": "ec4f9c9e-3508-4f39-be96-f1e5bb1ce465",
              "parentUUID": "52e1a080-3fb3-42db-bb3d-a1da20bbcfaf",
              "isHook": false,
              "skipped": false
            },
            {
              "title": "create reservation to delete",
              "fullTitle": " Test suite 2 create reservation to delete",
              "timedOut": null,
              "duration": 11993,
              "state": "passed",
              "speed": "slow",
              "pass": true,
              "fail": false,
              "pending": false,
              "context": null,
              "code": "indexfunctions.performValidLogin(cy, targets.username, targets.password, 'Tester Hotel Overview');\nreservationsPagefunctions.createaReservationtodelete(cy, 'Reservations');\ndashBoardfunctions.logout(cy, 'Login');",
              "err": {},
              "uuid": "70f38030-71a2-415b-866a-58c534d8fa7c",
              "parentUUID": "52e1a080-3fb3-42db-bb3d-a1da20bbcfaf",
              "isHook": false,
              "skipped": false
            }
          ],
          "suites": [],
          "passes": [
            "c81282ec-6921-43c7-958d-5b294262e637",
            "70560249-4ff8-41dd-8758-9bb41c972da1",
            "ec4f9c9e-3508-4f39-be96-f1e5bb1ce465",
            "70f38030-71a2-415b-866a-58c534d8fa7c"
          ],
          "failures": [],
          "pending": [],
          "skipped": [],
          "duration": 42933,
          "root": false,
          "rootEmpty": false,
          "_timeout": 2000
        }
      ],
      "passes": [],
      "failures": [],
      "pending": [],
      "skipped": [],
      "duration": 0,
      "root": true,
      "rootEmpty": true,
      "_timeout": 2000
    },
    {
      "uuid": "35cfd260-0657-4ef5-95bb-8939f725b731",
      "title": "",
      "fullFile": "cypress/integration/regressionpageobjects3.spec.js",
      "file": "cypress/integration/regressionpageobjects3.spec.js",
      "beforeHooks": [],
      "afterHooks": [],
      "tests": [],
      "suites": [
        {
          "uuid": "c8f2fd1d-a9bd-47e0-8d9f-c5a16aa67cd8",
          "title": " Test suite",
          "fullFile": "",
          "file": "",
          "beforeHooks": [],
          "afterHooks": [],
          "tests": [
            {
              "title": "create bill and delete it",
              "fullTitle": " Test suite create bill and delete it",
              "timedOut": null,
              "duration": 12644,
              "state": "passed",
              "speed": "slow",
              "pass": true,
              "fail": false,
              "pending": false,
              "context": null,
              "code": "indexfunctions.performValidLogin(cy, targets.username, targets.password, 'Tester Hotel Overview');\nbillsPagefunctions.createBillandDelete(cy, 'Bills');\ndashBoardfunctions.logout(cy, 'Login');",
              "err": {},
              "uuid": "d4e4c57b-12f6-4a57-854b-7a6a7ceb0ed0",
              "parentUUID": "c8f2fd1d-a9bd-47e0-8d9f-c5a16aa67cd8",
              "isHook": false,
              "skipped": false
            },
            {
              "title": "create client and delete it",
              "fullTitle": " Test suite create client and delete it",
              "timedOut": null,
              "duration": 8787,
              "state": "passed",
              "speed": "slow",
              "pass": true,
              "fail": false,
              "pending": false,
              "context": null,
              "code": "indexfunctions.performValidLogin(cy, targets.username, targets.password, 'Tester Hotel Overview');\nclientsPagefunctions.createclientanddelete(cy, 'Clients');\ndashBoardfunctions.logout(cy, 'Login');",
              "err": {},
              "uuid": "72d683f0-cae4-430c-a220-8381a0675ab9",
              "parentUUID": "c8f2fd1d-a9bd-47e0-8d9f-c5a16aa67cd8",
              "isHook": false,
              "skipped": false
            },
            {
              "title": "create reservation",
              "fullTitle": " Test suite create reservation",
              "timedOut": null,
              "duration": 10399,
              "state": "passed",
              "speed": "slow",
              "pass": true,
              "fail": false,
              "pending": false,
              "context": null,
              "code": "indexfunctions.performValidLogin(cy, targets.username, targets.password, 'Tester Hotel Overview');\nreservationsPagefunctions.createreservation(cy, 'Reservations');\ndashBoardfunctions.logout(cy, 'Login');",
              "err": {},
              "uuid": "f3b42d9a-ca86-48bd-ae35-0fae2d721193",
              "parentUUID": "c8f2fd1d-a9bd-47e0-8d9f-c5a16aa67cd8",
              "isHook": false,
              "skipped": false
            }
          ],
          "suites": [],
          "passes": [
            "d4e4c57b-12f6-4a57-854b-7a6a7ceb0ed0",
            "72d683f0-cae4-430c-a220-8381a0675ab9",
            "f3b42d9a-ca86-48bd-ae35-0fae2d721193"
          ],
          "failures": [],
          "pending": [],
          "skipped": [],
          "duration": 31830,
          "root": false,
          "rootEmpty": false,
          "_timeout": 2000
        }
      ],
      "passes": [],
      "failures": [],
      "pending": [],
      "skipped": [],
      "duration": 0,
      "root": true,
      "rootEmpty": true,
      "_timeout": 2000
    }
  ],
  "meta": {
    "mocha": {
      "version": "7.0.1"
    },
    "mochawesome": {
      "options": {
        "quiet": false,
        "reportFilename": "mochawesome",
        "saveHtml": false,
        "saveJson": true,
        "consoleReporter": "spec",
        "useInlineDiffs": false,
        "code": true
      },
      "version": "6.2.2"
    },
    "marge": {
      "options": {
        "charts": true,
        "overwrite": false,
        "html": false,
        "json": true,
        "reportDir": "cypress/report/mochawesome-report"
      },
      "version": "5.2.0"
    }
  }
}